{
  "kind": "collectionType",
  "collectionName": "audience",
  "info": {
    "singularName": "audience",
    "pluralName": "audiences",
    "displayName": "Audience",
    "name": "audience",
    "description": ""
  },
  "options": {
    "increments": true,
    "comment": "Audience",
    "draftAndPublish": false
  },
  "attributes": {
    "name": {
      "type": "string",
      "required": true
    },
    "key": {
      "type": "uid",
      "targetField": "name"
    }
  }
}
